[{"author":"Sam Haysom","description":"Vampires, serial killers, and chattery teeth.","publishedAt":0,"title":"13 of the best Stephen King short stories you've never read","url":"http://mashable.com/2017/05/20/best-stephen-king-short-stories/","urlToImage":"http://i.amz.mshcdn.com/82VEGPv0sCKFADrmsYhpzaK1qOA=/1200x630/2017%2F05%2F18%2F47%2F402616bc72f0468d8792a897d6afa139.00b32.jpg","score":12.171964,"fetchedAt":0},{"author":"Nick Statt","description":"The tech industry is full of blood-thirsty vampires","publishedAt":0,"title":"HBO’s Silicon Valley perfectly skewers the industry’s lust to live forever","url":"https://www.theverge.com/2017/5/22/15676696/hbo-silicon-valley-recap-season-4-episode-5-the-blood-boy","urlToImage":"https://cdn0.vox-cdn.com/thumbor/TRlgRA2Fa-Xy8KaZKseaZmDu2nQ=/0x0:1200x675/1600x900/cdn0.vox-cdn.com/uploads/chorus_image/image/54895543/silicon_valley_season_4_episode_5_1.0.jpg","score":11.491864,"fetchedAt":0}]