[{"lang":"es","resource":"Leonardo_da_Vinci","statCounter":486,"score":0.0,"thumbnail":"http://commons.wikimedia.org/wiki/Special:FilePath/Francesco_Melzi_-_Portrait_of_Leonardo_-_WGA14795.jpg?width=300","depiction":"http://commons.wikimedia.org/wiki/Special:FilePath/Francesco_Melzi_-_Portrait_of_Leonardo_-_WGA14795.jpg","label":"Leonardo da Vinci"},{"lang":"en","resource":"Drake_(musician)","statCounter":532,"score":0.0,"thumbnail":"http://commons.wikimedia.org/wiki/Special:FilePath/Drake_Bluesfest.jpg?width=300","depiction":"http://commons.wikimedia.org/wiki/Special:FilePath/Drake_Bluesfest.jpg","label":"Drake (musician)"},{"lang":"pl","resource":"Maria_Antonina_Austriaczka","statCounter":1165,"score":0.0,"thumbnail":"http://commons.wikimedia.org/wiki/Special:FilePath/Louise_Elisabeth_Vigée-Lebrun_-_Marie-Antoinette_dit_«_à_la_Rose_»_-_Google_Art_Project.jpg?width=300","depiction":"http://commons.wikimedia.org/wiki/Special:FilePath/Louise_Elisabeth_Vigée-Lebrun_-_Marie-Antoinette_dit_«_à_la_Rose_»_-_Google_Art_Project.jpg","label":"Maria Antonina Austriaczka"},{"lang":"en","resource":"John_Mayer","statCounter":489,"score":0.0,"thumbnail":"http://commons.wikimedia.org/wiki/Special:FilePath/John_Mayer_live_in_2007_01.png?width=300","depiction":"http://commons.wikimedia.org/wiki/Special:FilePath/John_Mayer_live_in_2007_01.png","label":"John Mayer"},{"lang":"pt","resource":"Manoel_de_Oliveira","statCounter":553,"score":0.0,"thumbnail":"http://commons.wikimedia.org/wiki/Special:FilePath/Manoel_de_Oliveira_3_juillet_2008-2.jpg?width=300","depiction":"http://commons.wikimedia.org/wiki/Special:FilePath/Manoel_de_Oliveira_3_juillet_2008-2.jpg","label":"Manoel de Oliveira"},{"lang":"it","resource":"Gian_Emilio_Malerba","statCounter":1099,"score":0.0,"thumbnail":"http://commons.wikimedia.org/wiki/Special:FilePath/Gian_Emilio_Malerba_-_Maschere.jpg?width=300","depiction":"http://commons.wikimedia.org/wiki/Special:FilePath/Gian_Emilio_Malerba_-_Maschere.jpg","label":"Gian Emilio Malerba"},{"lang":"en","resource":"Rhodesia","statCounter":843,"score":0.0,"thumbnail":"http://commons.wikimedia.org/wiki/Special:FilePath/Flag_of_Rhodesia_(1964).svg?width=300","depiction":"http://commons.wikimedia.org/wiki/Special:FilePath/Flag_of_Rhodesia_(1964).svg","label":"Rhodesia"},{"lang":"en","resource":"Carl_Reiner","statCounter":784,"score":0.0,"thumbnail":"http://commons.wikimedia.org/wiki/Special:FilePath/Carl_Reiner-1976.jpg?width=300","depiction":"http://commons.wikimedia.org/wiki/Special:FilePath/Carl_Reiner-1976.jpg","label":"Carl Reiner"},{"lang":"ja","resource":"松下優也","statCounter":1296,"score":0.0,"thumbnail":"http://commons.wikimedia.org/wiki/Special:FilePath/Yuya_Matsushita_at_Fanime_2011_Opening_Ceremony.jpg?width=300","depiction":"http://commons.wikimedia.org/wiki/Special:FilePath/Yuya_Matsushita_at_Fanime_2011_Opening_Ceremony.jpg","label":"松下優也"},{"lang":"fr","resource":"Virginie_Efira","statCounter":645,"score":0.0,"thumbnail":"http://commons.wikimedia.org/wiki/Special:FilePath/Virginie_Efira_2016.jpg?width=300","depiction":"http://commons.wikimedia.org/wiki/Special:FilePath/Virginie_Efira_2016.jpg","label":"Virginie Efira"},{"lang":"ru","resource":"Заха,_Уилфрид","statCounter":781,"score":0.0,"thumbnail":"http://commons.wikimedia.org/wiki/Special:FilePath/Wilfried_Zaha.jpg?width=300","depiction":"http://commons.wikimedia.org/wiki/Special:FilePath/Wilfried_Zaha.jpg","label":"Заха, Уилфрид"},{"lang":"ru","resource":"Мата_Хари","statCounter":530,"score":0.0,"thumbnail":"http://commons.wikimedia.org/wiki/Special:FilePath/Mata_Mari_14.jpg?width=300","depiction":"http://commons.wikimedia.org/wiki/Special:FilePath/Mata_Mari_14.jpg","label":"Мата Хари"},{"lang":"en","resource":"Education_in_Hong_Kong","statCounter":352,"score":0.0,"thumbnail":"http://commons.wikimedia.org/wiki/Special:FilePath/Hong_Kong_SAR_Regional_Emblem.svg?width=300","depiction":"http://commons.wikimedia.org/wiki/Special:FilePath/Hong_Kong_SAR_Regional_Emblem.svg","label":"Education in Hong Kong"},{"lang":"en","resource":"Palace_of_Westminster","statCounter":718,"score":0.0,"thumbnail":"http://commons.wikimedia.org/wiki/Special:FilePath/Parliament_at_Sunset.JPG?width=300","depiction":"http://commons.wikimedia.org/wiki/Special:FilePath/Parliament_at_Sunset.JPG","label":"Palace of Westminster"},{"lang":"en","resource":"Alicia_Keys","statCounter":832,"score":0.0,"thumbnail":"http://commons.wikimedia.org/wiki/Special:FilePath/AliciaKeys2013.jpg?width=300","depiction":"http://commons.wikimedia.org/wiki/Special:FilePath/AliciaKeys2013.jpg","label":"Alicia Keys"},{"lang":"en","resource":"Xavier_University","statCounter":577,"score":0.0,"thumbnail":"http://commons.wikimedia.org/wiki/Special:FilePath/Xavier_University_(Cincinnati)_seal.png?width=300","depiction":"http://commons.wikimedia.org/wiki/Special:FilePath/Xavier_University_(Cincinnati)_seal.png","label":"Xavier University"},{"lang":"ru","resource":"Самойлова,_Юлия_Олеговна","statCounter":353,"score":0.0,"thumbnail":"http://commons.wikimedia.org/wiki/Special:FilePath/Julia_Samoylova_singer.jpg?width=300","depiction":"http://commons.wikimedia.org/wiki/Special:FilePath/Julia_Samoylova_singer.jpg","label":"Самойлова, Юлия Олеговна"},{"lang":"ru","resource":"1-510_(серия_домов)","statCounter":600,"score":0.0,"thumbnail":"http://commons.wikimedia.org/wiki/Special:FilePath/Серия_1-510.jpg?width=300","depiction":"http://commons.wikimedia.org/wiki/Special:FilePath/Серия_1-510.jpg","label":"1-510 (серия домов)"},{"lang":"fr","resource":"Christine_Angot","statCounter":2684,"score":0.0,"thumbnail":"http://commons.wikimedia.org/wiki/Special:FilePath/Christine_Angot_nineties.JPG?width=300","depiction":"http://commons.wikimedia.org/wiki/Special:FilePath/Christine_Angot_nineties.JPG","label":"Christine Angot"},{"lang":"fr","resource":"Île_Maurice","statCounter":1564,"score":0.0,"thumbnail":"http://commons.wikimedia.org/wiki/Special:FilePath/Mauritius_island_location.svg?width=300","depiction":"http://commons.wikimedia.org/wiki/Special:FilePath/Mauritius_island_location.svg","label":"Île Maurice"},{"lang":"en","resource":"Rachel_Carson","statCounter":1027,"score":0.0,"thumbnail":"http://commons.wikimedia.org/wiki/Special:FilePath/Rachel-Carson.jpg?width=300","depiction":"http://commons.wikimedia.org/wiki/Special:FilePath/Rachel-Carson.jpg","label":"Rachel Carson"},{"lang":"ru","resource":"Гордеев,_Вячеслав_Михайлович","statCounter":644,"score":0.0,"thumbnail":"http://commons.wikimedia.org/wiki/Special:FilePath/Thanks_the_President_of_the_Russian_Federation.PNG?width=300","depiction":"http://commons.wikimedia.org/wiki/Special:FilePath/Thanks_the_President_of_the_Russian_Federation.PNG","label":"Гордеев, Вячеслав Михайлович"},{"lang":"en","resource":"SourceFed","statCounter":563,"score":0.0,"thumbnail":"http://commons.wikimedia.org/wiki/Special:FilePath/SourceFed_logo_2013-08-25_00-26.jpg?width=300","depiction":"http://commons.wikimedia.org/wiki/Special:FilePath/SourceFed_logo_2013-08-25_00-26.jpg","label":"SourceFed"},{"lang":"en","resource":"Badrinath_Ki_Dulhania","statCounter":400,"score":0.0,"thumbnail":"http://en.wikipedia.org/wiki/Special:FilePath/Badrinath_ki_Dulhania.jpg?width=300","depiction":"http://en.wikipedia.org/wiki/Special:FilePath/Badrinath_ki_Dulhania.jpg","label":"Badrinath Ki Dulhania"},{"lang":"en","resource":"M23_chemical_mine","statCounter":843,"score":0.0,"thumbnail":"http://commons.wikimedia.org/wiki/Special:FilePath/Last_VX_mine_destroyed_at_JACADS.jpg?width=300","depiction":"http://commons.wikimedia.org/wiki/Special:FilePath/Last_VX_mine_destroyed_at_JACADS.jpg","label":"M23 chemical mine"},{"lang":"en","resource":"Special_education","statCounter":356,"score":0.0,"thumbnail":"http://commons.wikimedia.org/wiki/Special:FilePath/Skolegutt.jpg?width=300","depiction":"http://commons.wikimedia.org/wiki/Special:FilePath/Skolegutt.jpg","label":"Special education"},{"lang":"en","resource":"Rob_Reiner","statCounter":646,"score":0.0,"thumbnail":"http://commons.wikimedia.org/wiki/Special:FilePath/Rob_Reiner_MFF_2016.jpg?width=300","depiction":"http://commons.wikimedia.org/wiki/Special:FilePath/Rob_Reiner_MFF_2016.jpg","label":"Rob Reiner"},{"lang":"en","resource":"Patient_Protection_and_Affordable_Care_Act","statCounter":594,"score":0.0,"thumbnail":"http://commons.wikimedia.org/wiki/Special:FilePath/Barack_Obama_reacts_to_the_passing_of_Healthcare_bill.jpg?width=300","depiction":"http://commons.wikimedia.org/wiki/Special:FilePath/Barack_Obama_reacts_to_the_passing_of_Healthcare_bill.jpg","label":"Patient Protection and Affordable Care Act"},{"lang":"en","resource":"YouTube","statCounter":726,"score":0.0,"thumbnail":"http://commons.wikimedia.org/wiki/Special:FilePath/YouTube_logo_2015.svg?width=300","depiction":"http://commons.wikimedia.org/wiki/Special:FilePath/YouTube_logo_2015.svg","label":"YouTube"},{"lang":"en","resource":"Naomi_Scott","statCounter":505,"score":0.0,"thumbnail":"http://commons.wikimedia.org/wiki/Special:FilePath/Naomi_Scott.jpg?width=300","depiction":"http://commons.wikimedia.org/wiki/Special:FilePath/Naomi_Scott.jpg","label":"Naomi Scott"},{"lang":"fr","resource":"Badminton","statCounter":1139,"score":0.0,"thumbnail":"http://commons.wikimedia.org/wiki/Special:FilePath/Badminton_pictogram.svg?width=300","depiction":"http://commons.wikimedia.org/wiki/Special:FilePath/Badminton_pictogram.svg","label":"Badminton"},{"lang":"ja","resource":"フタバアオイ","statCounter":1353,"score":0.0,"thumbnail":"http://commons.wikimedia.org/wiki/Special:FilePath/Asarum_caulescens.JPG?width=300","depiction":"http://commons.wikimedia.org/wiki/Special:FilePath/Asarum_caulescens.JPG","label":"フタバアオイ"},{"lang":"it","resource":"Cino_Tortorella","statCounter":753,"score":0.0,"thumbnail":"http://it.wikipedia.org/wiki/Special:FilePath/Tortorella_1968.jpg?width=300","depiction":"http://it.wikipedia.org/wiki/Special:FilePath/Tortorella_1968.jpg","label":"Cino Tortorella"},{"lang":"ja","resource":"辰巳孝太郎","statCounter":1876,"score":0.0,"thumbnail":"http://commons.wikimedia.org/wiki/Special:FilePath/Emerson_College,_Boston_MA.jpg?width=300","depiction":"http://commons.wikimedia.org/wiki/Special:FilePath/Emerson_College,_Boston_MA.jpg","label":"辰巳孝太郎"},{"lang":"fr","resource":"Salouen","statCounter":900,"score":0.0,"thumbnail":"http://commons.wikimedia.org/wiki/Special:FilePath/Chine_208.jpg?width=300","depiction":"http://commons.wikimedia.org/wiki/Special:FilePath/Chine_208.jpg","label":"Salouen"},{"lang":"ja","resource":"照ノ富士春雄","statCounter":647,"score":0.0,"thumbnail":"http://commons.wikimedia.org/wiki/Special:FilePath/Terunofuji_2014.jpg?width=300","depiction":"http://commons.wikimedia.org/wiki/Special:FilePath/Terunofuji_2014.jpg","label":"照ノ富士春雄"},{"lang":"en","resource":"RSS","statCounter":420,"score":0.0,"thumbnail":"http://en.wikipedia.org/wiki/Special:FilePath/Feed-icon.svg?width=300","depiction":"http://en.wikipedia.org/wiki/Special:FilePath/Feed-icon.svg","label":"RSS"},{"lang":"en","resource":"Rodney_Frelinghuysen","statCounter":673,"score":0.0,"thumbnail":"http://commons.wikimedia.org/wiki/Special:FilePath/Rodney_Frelinghuysen_official_photo,_114th_Congress.jpg?width=300","depiction":"http://commons.wikimedia.org/wiki/Special:FilePath/Rodney_Frelinghuysen_official_photo,_114th_Congress.jpg","label":"Rodney Frelinghuysen"},{"lang":"ru","resource":"Кот-д’Ивуар","statCounter":638,"score":0.0,"thumbnail":"http://commons.wikimedia.org/wiki/Special:FilePath/Coat_of_arms_of_Ivory_Coast.svg?width=300","depiction":"http://commons.wikimedia.org/wiki/Special:FilePath/Coat_of_arms_of_Ivory_Coast.svg","label":"Кот-д’Ивуар"},{"lang":"ja","resource":"おおかみこどもの雨と雪","statCounter":4943,"score":0.0,"thumbnail":"http://commons.wikimedia.org/wiki/Special:FilePath/Okami_Kodomo_no_Ame_to_Yuki_(Logo).svg?width=300","depiction":"http://commons.wikimedia.org/wiki/Special:FilePath/Okami_Kodomo_no_Ame_to_Yuki_(Logo).svg","label":"おおかみこどもの雨と雪"},{"lang":"de","resource":"Halle_Berry","statCounter":973,"score":0.0,"thumbnail":"http://commons.wikimedia.org/wiki/Special:FilePath/Halle_Berry_by_Gage_Skidmore.jpg?width=300","depiction":"http://commons.wikimedia.org/wiki/Special:FilePath/Halle_Berry_by_Gage_Skidmore.jpg","label":"Halle Berry"},{"lang":"es","resource":"Bacteria","statCounter":677,"score":0.0,"thumbnail":"http://commons.wikimedia.org/wiki/Special:FilePath/EscherichiaColi_NIAID.jpg?width=300","depiction":"http://commons.wikimedia.org/wiki/Special:FilePath/EscherichiaColi_NIAID.jpg","label":"Bacteria"},{"lang":"en","resource":"Insurance","statCounter":391,"score":0.0,"thumbnail":"http://commons.wikimedia.org/wiki/Special:FilePath/Algemeene_Verzeekering-Maatschappij_Providentia.jpg?width=300","depiction":"http://commons.wikimedia.org/wiki/Special:FilePath/Algemeene_Verzeekering-Maatschappij_Providentia.jpg","label":"Insurance"},{"lang":"pt","resource":"Baralho","statCounter":592,"score":0.0,"thumbnail":"http://commons.wikimedia.org/wiki/Special:FilePath/A_studio_image_of_a_hand_of_playing_cards._MOD_45148377.jpg?width=300","depiction":"http://commons.wikimedia.org/wiki/Special:FilePath/A_studio_image_of_a_hand_of_playing_cards._MOD_45148377.jpg","label":"Baralho"},{"lang":"en","resource":"Human_overpopulation","statCounter":381,"score":0.0,"thumbnail":"http://commons.wikimedia.org/wiki/Special:FilePath/Population_curve.svg?width=300","depiction":"http://commons.wikimedia.org/wiki/Special:FilePath/Population_curve.svg","label":"Human overpopulation"},{"lang":"en","resource":"Selena","statCounter":2347,"score":0.0,"thumbnail":"http://en.wikipedia.org/wiki/Special:FilePath/SelenaQSignature.svg?width=300","depiction":"http://en.wikipedia.org/wiki/Special:FilePath/SelenaQSignature.svg","label":"Selena"},{"lang":"en","resource":"Mark_Few","statCounter":655,"score":0.0,"thumbnail":"http://commons.wikimedia.org/wiki/Special:FilePath/Mark-few-USD-vs-Gonzaga-feb-18-08.jpg?width=300","depiction":"http://commons.wikimedia.org/wiki/Special:FilePath/Mark-few-USD-vs-Gonzaga-feb-18-08.jpg","label":"Mark Few"},{"lang":"en","resource":"Primary_education","statCounter":355,"score":0.0,"thumbnail":"http://commons.wikimedia.org/wiki/Special:FilePath/Millennium_Development_Goals,_UN_Headquarters,_New_York_City,_New_York_-_20080501.jpg?width=300","depiction":"http://commons.wikimedia.org/wiki/Special:FilePath/Millennium_Development_Goals,_UN_Headquarters,_New_York_City,_New_York_-_20080501.jpg","label":"Primary education"},{"lang":"ja","resource":"明神礁","statCounter":405,"score":0.0,"thumbnail":"http://commons.wikimedia.org/wiki/Special:FilePath/Myojin-sho.jpg?width=300","depiction":"http://commons.wikimedia.org/wiki/Special:FilePath/Myojin-sho.jpg","label":"明神礁"},{"lang":"pl","resource":"Puchar_Świata_w_skokach_narciarskich_2016/2017","statCounter":890,"score":0.0,"thumbnail":"http://commons.wikimedia.org/wiki/Special:FilePath/Ski_jumping_pictogram.svg?width=300","depiction":"http://commons.wikimedia.org/wiki/Special:FilePath/Ski_jumping_pictogram.svg","label":"Puchar Świata w skokach narciarskich 2016/2017"},{"lang":"en","resource":"Lonzo_Ball","statCounter":814,"score":0.0,"thumbnail":"http://commons.wikimedia.org/wiki/Special:FilePath/20160330_MCDAAG_Lonzo_Ball_handle.jpg?width=300","depiction":"http://commons.wikimedia.org/wiki/Special:FilePath/20160330_MCDAAG_Lonzo_Ball_handle.jpg","label":"Lonzo Ball"},{"lang":"ja","resource":"小池晃","statCounter":589,"score":0.0,"thumbnail":"http://commons.wikimedia.org/wiki/Special:FilePath/Akira_Koike.jpg?width=300","depiction":"http://commons.wikimedia.org/wiki/Special:FilePath/Akira_Koike.jpg","label":"小池晃"},{"lang":"en","resource":"Norman_Reedus","statCounter":607,"score":0.0,"thumbnail":"http://commons.wikimedia.org/wiki/Special:FilePath/Norman_Reedus_2016_(cropped).jpg?width=300","depiction":"http://commons.wikimedia.org/wiki/Special:FilePath/Norman_Reedus_2016_(cropped).jpg","label":"Norman Reedus"},{"lang":"en","resource":"Elizabeth_I_of_England","statCounter":618,"score":0.0,"thumbnail":"http://en.wikipedia.org/wiki/Special:FilePath/Darnley_stage_3.jpg?width=300","depiction":"http://en.wikipedia.org/wiki/Special:FilePath/Darnley_stage_3.jpg","label":"Elizabeth I of England"},{"lang":"es","resource":"Segunda_Guerra_Mundial","statCounter":830,"score":0.0,"thumbnail":"http://commons.wikimedia.org/wiki/Special:FilePath/WW2Montage.PNG?width=300","depiction":"http://commons.wikimedia.org/wiki/Special:FilePath/WW2Montage.PNG","label":"Segunda Guerra Mundial"},{"lang":"en","resource":"Brazil_national_football_team","statCounter":484,"score":0.0,"thumbnail":"http://commons.wikimedia.org/wiki/Special:FilePath/Brazil_national_1914.jpg?width=300","depiction":"http://commons.wikimedia.org/wiki/Special:FilePath/Brazil_national_1914.jpg","label":"Brazil national football team"},{"lang":"en","resource":"Sadiq_Khan","statCounter":573,"score":0.0,"thumbnail":"http://commons.wikimedia.org/wiki/Special:FilePath/Sadiq_Khan.png?width=300","depiction":"http://commons.wikimedia.org/wiki/Special:FilePath/Sadiq_Khan.png","label":"Sadiq Khan"},{"lang":"es","resource":"Renacimiento","statCounter":483,"score":0.0,"thumbnail":"http://commons.wikimedia.org/wiki/Special:FilePath/Vitruvian.jpg?width=300","depiction":"http://commons.wikimedia.org/wiki/Special:FilePath/Vitruvian.jpg","label":"Renacimiento"},{"lang":"ru","resource":"Тимати","statCounter":732,"score":0.0,"thumbnail":"http://ru.wikipedia.org/wiki/Special:FilePath/Автограф_Тимати.jpg?width=300","depiction":"http://ru.wikipedia.org/wiki/Special:FilePath/Автограф_Тимати.jpg","label":"Тимати"},{"lang":"en","resource":"Sakuradamon_Incident_(1860)","statCounter":575,"score":0.0,"thumbnail":"http://commons.wikimedia.org/wiki/Special:FilePath/Ii_Naosuke.jpg?width=300","depiction":"http://commons.wikimedia.org/wiki/Special:FilePath/Ii_Naosuke.jpg","label":"Sakuradamon Incident (1860)"},{"lang":"es","resource":"Arroba_(símbolo)","statCounter":999,"score":0.0,"thumbnail":"http://commons.wikimedia.org/wiki/Special:FilePath/At_sign.svg?width=300","depiction":"http://commons.wikimedia.org/wiki/Special:FilePath/At_sign.svg","label":"Arroba (símbolo)"},{"lang":"fr","resource":"Pierre_Bérégovoy","statCounter":699,"score":0.0,"thumbnail":"http://commons.wikimedia.org/wiki/Special:FilePath/Pierre_Beregovoy.jpg?width=300","depiction":"http://commons.wikimedia.org/wiki/Special:FilePath/Pierre_Beregovoy.jpg","label":"Pierre Bérégovoy"},{"lang":"it","resource":"Trattato_che_istituisce_la_Comunità_economica_europea","statCounter":426,"score":0.0,"thumbnail":"http://it.wikipedia.org/wiki/Special:FilePath/Firma_dei_trattati_di_Roma_(1957).jpg?width=300","depiction":"http://it.wikipedia.org/wiki/Special:FilePath/Firma_dei_trattati_di_Roma_(1957).jpg","label":"Trattato che istituisce la Comunità economica europea"},{"lang":"es","resource":"Día_Mundial_del_Agua","statCounter":606,"score":0.0,"thumbnail":"http://commons.wikimedia.org/wiki/Special:FilePath/Iceberg_1_1997_08_07.jpg?width=300","depiction":"http://commons.wikimedia.org/wiki/Special:FilePath/Iceberg_1_1997_08_07.jpg","label":"Día Mundial del Agua"},{"lang":"en","resource":"Gonzaga_University","statCounter":741,"score":0.0,"thumbnail":"http://commons.wikimedia.org/wiki/Special:FilePath/Gonzaga_University_360.jpg?width=300","depiction":"http://commons.wikimedia.org/wiki/Special:FilePath/Gonzaga_University_360.jpg","label":"Gonzaga University"},{"lang":"es","resource":"Expropiación_del_petróleo_en_México","statCounter":505,"score":0.0,"thumbnail":"http://commons.wikimedia.org/wiki/Special:FilePath/GLORIETA_DE_PETROLEOS_MEXICANOS.jpg?width=300","depiction":"http://commons.wikimedia.org/wiki/Special:FilePath/GLORIETA_DE_PETROLEOS_MEXICANOS.jpg","label":"Expropiación del petróleo en México"},{"lang":"pl","resource":"Wojciech_Młynarski","statCounter":1260,"score":0.0,"thumbnail":"http://commons.wikimedia.org/wiki/Special:FilePath/Wojciech_Mlynarski.jpg?width=300","depiction":"http://commons.wikimedia.org/wiki/Special:FilePath/Wojciech_Mlynarski.jpg","label":"Wojciech Młynarski"},{"lang":"en","resource":"Boris_Yeltsin","statCounter":1809,"score":0.0,"thumbnail":"http://commons.wikimedia.org/wiki/Special:FilePath/Boris_Yeltsin.jpg?width=300","depiction":"http://commons.wikimedia.org/wiki/Special:FilePath/Boris_Yeltsin.jpg","label":"Boris Yeltsin"},{"lang":"en","resource":"Education_in_Japan","statCounter":354,"score":0.0,"thumbnail":"http://en.wikipedia.org/wiki/Special:FilePath/Flag_of_Japan.svg?width=300","depiction":"http://en.wikipedia.org/wiki/Special:FilePath/Flag_of_Japan.svg","label":"Education in Japan"},{"lang":"en","resource":"2017_Formula_One_season","statCounter":409,"score":0.0,"thumbnail":"http://commons.wikimedia.org/wiki/Special:FilePath/Nico_Rosberg_2016_Malaysia_FP2.jpg?width=300","depiction":"http://commons.wikimedia.org/wiki/Special:FilePath/Nico_Rosberg_2016_Malaysia_FP2.jpg","label":"2017 Formula One season"},{"lang":"de","resource":"Gil_Ofarim","statCounter":609,"score":0.0,"thumbnail":"http://commons.wikimedia.org/wiki/Special:FilePath/Gil_Ofarim_Oldenburg.jpg?width=300","depiction":"http://commons.wikimedia.org/wiki/Special:FilePath/Gil_Ofarim_Oldenburg.jpg","label":"Gil Ofarim"},{"lang":"de","resource":"Rosi_Mittermaier","statCounter":699,"score":0.0,"thumbnail":"http://commons.wikimedia.org/wiki/Special:FilePath/Rosi_Mittermaier_BAD.JPG?width=300","depiction":"http://commons.wikimedia.org/wiki/Special:FilePath/Rosi_Mittermaier_BAD.JPG","label":"Rosi Mittermaier"},{"lang":"en","resource":"Paulinho_(footballer)","statCounter":596,"score":0.0,"thumbnail":"http://commons.wikimedia.org/wiki/Special:FilePath/Jose_Paulo_Bezerra_Maciel_Junior_2013.jpg?width=300","depiction":"http://commons.wikimedia.org/wiki/Special:FilePath/Jose_Paulo_Bezerra_Maciel_Junior_2013.jpg","label":"Paulinho (footballer)"},{"lang":"en","resource":"Cory_Booker","statCounter":639,"score":0.0,"thumbnail":"http://commons.wikimedia.org/wiki/Special:FilePath/Cory_Booker,_official_portrait,_114th_Congress.jpg?width=300","depiction":"http://commons.wikimedia.org/wiki/Special:FilePath/Cory_Booker,_official_portrait,_114th_Congress.jpg","label":"Cory Booker"},{"lang":"en","resource":"Dwayne_Johnson","statCounter":491,"score":0.0,"thumbnail":"http://commons.wikimedia.org/wiki/Special:FilePath/Dwayne_Johnson_Hercules_2014_(cropped).jpg?width=300","depiction":"http://commons.wikimedia.org/wiki/Special:FilePath/Dwayne_Johnson_Hercules_2014_(cropped).jpg","label":"Dwayne Johnson"},{"lang":"pl","resource":"Murad_IV","statCounter":944,"score":0.0,"thumbnail":"http://commons.wikimedia.org/wiki/Special:FilePath/Murad_IV.jpg?width=300","depiction":"http://commons.wikimedia.org/wiki/Special:FilePath/Murad_IV.jpg","label":"Murad IV"},{"lang":"de","resource":"Bastiaan_Ragas","statCounter":925,"score":0.0,"thumbnail":"http://commons.wikimedia.org/wiki/Special:FilePath/Bastiaan_ragas-1442683947.jpg?width=300","depiction":"http://commons.wikimedia.org/wiki/Special:FilePath/Bastiaan_ragas-1442683947.jpg","label":"Bastiaan Ragas"},{"lang":"nl","resource":"Overijssel","statCounter":512,"score":0.0,"thumbnail":"http://commons.wikimedia.org/wiki/Special:FilePath/Flag_Overijssel.svg?width=300","depiction":"http://commons.wikimedia.org/wiki/Special:FilePath/Flag_Overijssel.svg","label":"Overijssel"},{"lang":"en","resource":"Dax_Shepard","statCounter":611,"score":0.0,"thumbnail":"http://commons.wikimedia.org/wiki/Special:FilePath/Dax_Shepard_Paleyfest_2013.jpg?width=300","depiction":"http://commons.wikimedia.org/wiki/Special:FilePath/Dax_Shepard_Paleyfest_2013.jpg","label":"Dax Shepard"},{"lang":"en","resource":"Franklin_D._Roosevelt","statCounter":1006,"score":0.0,"thumbnail":"http://commons.wikimedia.org/wiki/Special:FilePath/Franklin_Roosevelt_Signature.svg?width=300","depiction":"http://commons.wikimedia.org/wiki/Special:FilePath/Franklin_Roosevelt_Signature.svg","label":"Franklin D. Roosevelt"},{"lang":"ja","resource":"安倍昭恵","statCounter":9707,"score":0.0,"thumbnail":"http://commons.wikimedia.org/wiki/Special:FilePath/AkieAbe,_2007Apr27.jpg?width=300","depiction":"http://commons.wikimedia.org/wiki/Special:FilePath/AkieAbe,_2007Apr27.jpg","label":"安倍昭恵"},{"lang":"fr","resource":"Professeur_Choron","statCounter":671,"score":0.0,"thumbnail":"http://commons.wikimedia.org/wiki/Special:FilePath/Defaut.svg?width=300","depiction":"http://commons.wikimedia.org/wiki/Special:FilePath/Defaut.svg","label":"Professeur Choron"},{"lang":"en","resource":"Earth","statCounter":2464,"score":0.0,"thumbnail":"http://commons.wikimedia.org/wiki/Special:FilePath/Earth_symbol.svg?width=300","depiction":"http://commons.wikimedia.org/wiki/Special:FilePath/Earth_symbol.svg","label":"Earth"},{"lang":"en","resource":"Piano_Concerto_No._24_(Mozart)","statCounter":885,"score":0.0,"thumbnail":"http://commons.wikimedia.org/wiki/Special:FilePath/Wolfgang-amadeus-mozart_1.jpg?width=300","depiction":"http://commons.wikimedia.org/wiki/Special:FilePath/Wolfgang-amadeus-mozart_1.jpg","label":"Piano Concerto No. 24 (Mozart)"},{"lang":"en","resource":"HTML","statCounter":428,"score":0.0,"thumbnail":"http://commons.wikimedia.org/wiki/Special:FilePath/HTML.svg?width=300","depiction":"http://commons.wikimedia.org/wiki/Special:FilePath/HTML.svg","label":"HTML"},{"lang":"fr","resource":"Jean_Seberg","statCounter":1225,"score":0.0,"thumbnail":"http://commons.wikimedia.org/wiki/Special:FilePath/Camorra_Jean_Seberg.png?width=300","depiction":"http://commons.wikimedia.org/wiki/Special:FilePath/Camorra_Jean_Seberg.png","label":"Jean Seberg"},{"lang":"en","resource":"Lali_Espósito","statCounter":532,"score":0.0,"thumbnail":"http://commons.wikimedia.org/wiki/Special:FilePath/Lali_Espósito_2012.jpg?width=300","depiction":"http://commons.wikimedia.org/wiki/Special:FilePath/Lali_Espósito_2012.jpg","label":"Lali Espósito"},{"lang":"en","resource":"Séamus_Coleman","statCounter":626,"score":0.0,"thumbnail":"http://commons.wikimedia.org/wiki/Special:FilePath/FIFA_WC-qualification_2014_-_Austria_vs_Ireland_2013-09-10_-_Seamus_Coleman_02.jpg?width=300","depiction":"http://commons.wikimedia.org/wiki/Special:FilePath/FIFA_WC-qualification_2014_-_Austria_vs_Ireland_2013-09-10_-_Seamus_Coleman_02.jpg","label":"Séamus Coleman"},{"lang":"de","resource":"Tatort:_Reifezeugnis","statCounter":616,"score":0.0,"thumbnail":"http://commons.wikimedia.org/wiki/Special:FilePath/Tatort_Logo_mini.svg?width=300","depiction":"http://commons.wikimedia.org/wiki/Special:FilePath/Tatort_Logo_mini.svg","label":"Tatort: Reifezeugnis"},{"lang":"en","resource":"How_I_Unleashed_World_War_II","statCounter":804,"score":0.0,"thumbnail":"http://commons.wikimedia.org/wiki/Special:FilePath/Przybliżona_trasa_Franciszka_Dolasa_w_serialu_Jak_rozpętałem_II_wojnę_światową.png?width=300","depiction":"http://commons.wikimedia.org/wiki/Special:FilePath/Przybliżona_trasa_Franciszka_Dolasa_w_serialu_Jak_rozpętałem_II_wojnę_światową.png","label":"How I Unleashed World War II"},{"lang":"nl","resource":"Afsluitdijk","statCounter":802,"score":0.0,"thumbnail":"http://commons.wikimedia.org/wiki/Special:FilePath/Map_of_Afsluitdijk.png?width=300","depiction":"http://commons.wikimedia.org/wiki/Special:FilePath/Map_of_Afsluitdijk.png","label":"Afsluitdijk"},{"lang":"en","resource":"Rōnin","statCounter":549,"score":0.0,"thumbnail":"http://commons.wikimedia.org/wiki/Special:FilePath/Miyamoto_Musashi_Painting.jpg?width=300","depiction":"http://commons.wikimedia.org/wiki/Special:FilePath/Miyamoto_Musashi_Painting.jpg","label":"Rōnin"},{"lang":"es","resource":"Distribución_geográfica_del_idioma_español","statCounter":606,"score":0.0,"thumbnail":"http://commons.wikimedia.org/wiki/Special:FilePath/Buenos_Aires_-_Obelisco_-_20130312_144258.jpg?width=300","depiction":"http://commons.wikimedia.org/wiki/Special:FilePath/Buenos_Aires_-_Obelisco_-_20130312_144258.jpg","label":"Distribución geográfica del idioma español"},{"lang":"en","resource":"Grey's_Anatomy","statCounter":537,"score":0.0,"thumbnail":"http://commons.wikimedia.org/wiki/Special:FilePath/Grey's_Anatomy_Logo.svg?width=300","depiction":"http://commons.wikimedia.org/wiki/Special:FilePath/Grey's_Anatomy_Logo.svg","label":"Grey's Anatomy"},{"lang":"en","resource":"Betty_Who","statCounter":1230,"score":0.0,"thumbnail":"http://commons.wikimedia.org/wiki/Special:FilePath/2014-06-08_15-23-45bettywho.JPG?width=300","depiction":"http://commons.wikimedia.org/wiki/Special:FilePath/2014-06-08_15-23-45bettywho.JPG","label":"Betty Who"},{"lang":"el","resource":"Παπαφλέσσας","statCounter":664,"score":0.0,"thumbnail":"http://el.wikipedia.org/wiki/Special:FilePath/Papaflesas.jpg?width=300","depiction":"http://el.wikipedia.org/wiki/Special:FilePath/Papaflesas.jpg","label":"Παπαφλέσσας"},{"lang":"en","resource":"1993_Bishopsgate_bombing","statCounter":956,"score":0.0,"thumbnail":"http://commons.wikimedia.org/wiki/Special:FilePath/Ford_Iveco.jpg?width=300","depiction":"http://commons.wikimedia.org/wiki/Special:FilePath/Ford_Iveco.jpg","label":"1993 Bishopsgate bombing"},{"lang":"en","resource":"List_of_The_Big_Bang_Theory_episodes","statCounter":550,"score":0.0,"thumbnail":"http://commons.wikimedia.org/wiki/Special:FilePath/TBBT_logo.svg?width=300","depiction":"http://commons.wikimedia.org/wiki/Special:FilePath/TBBT_logo.svg","label":"List of The Big Bang Theory episodes"},{"lang":"en","resource":"Kevin_Costner","statCounter":637,"score":0.0,"thumbnail":"http://commons.wikimedia.org/wiki/Special:FilePath/Kevin_Costner_2014.jpg?width=300","depiction":"http://commons.wikimedia.org/wiki/Special:FilePath/Kevin_Costner_2014.jpg","label":"Kevin Costner"},{"lang":"ru","resource":"Путин,_Владимир_Владимирович","statCounter":1675,"score":0.0,"thumbnail":"http://commons.wikimedia.org/wiki/Special:FilePath/Standard_of_the_President_of_the_Russian_Federation.svg?width=300","depiction":"http://commons.wikimedia.org/wiki/Special:FilePath/Standard_of_the_President_of_the_Russian_Federation.svg","label":"Путин, Владимир Владимирович"}]